opensfdi/__init__.py
opensfdi/calibration.py
opensfdi/devices.py
opensfdi/fringe_projection.py
opensfdi/image.py
opensfdi/light/__init__.py
opensfdi/light/monte_carlo.py
opensfdi/phase.py
opensfdi/profilometry.py
opensfdi/services.py
opensfdi/utils/__init__.py
opensfdi/utils/colour.py
opensfdi/utils/fringes.py
opensfdi/utils/maths.py
opensfdi-0.1.8.dist-info/METADATA
opensfdi-0.1.8.dist-info/WHEEL
opensfdi-0.1.8.dist-info/RECORD
