Metadata-Version: 2.3
Name: opensfdi
Version: 0.1.8
Summary: 
Author: Daniel Weston
Author-email: psydw2@nottingham.ac.uk
Requires-Python: ==3.11.7
Classifier: Programming Language :: Python :: 3
Requires-Dist: imageio (>=2.34.2,<3.0.0)
Requires-Dist: matplotlib (>=3.9.1,<4.0.0)
Requires-Dist: numpy (>=2.0.1,<3.0.0)
Requires-Dist: opencv-python (>=4.10.0.84,<5.0.0.0)
Requires-Dist: pillow (>=10.4.0,<11.0.0)
Requires-Dist: pydantic (>=2.9.2,<3.0.0)
Requires-Dist: scikit-image (>=0.24.0,<0.25.0)
Requires-Dist: scikit-learn (>=1.5.1,<2.0.0)
Requires-Dist: scipy (>=1.14.0,<2.0.0)
